README.txt
setup.py
docs/HISTORY.txt
docs/LICENSE.GPL
docs/LICENSE.txt
raptus/__init__.py
raptus.recipe.torii.egg-info/PKG-INFO
raptus.recipe.torii.egg-info/SOURCES.txt
raptus.recipe.torii.egg-info/dependency_links.txt
raptus.recipe.torii.egg-info/entry_points.txt
raptus.recipe.torii.egg-info/namespace_packages.txt
raptus.recipe.torii.egg-info/not-zip-safe
raptus.recipe.torii.egg-info/requires.txt
raptus.recipe.torii.egg-info/top_level.txt
raptus/recipe/__init__.py
raptus/recipe/torii/README.txt
raptus/recipe/torii/__init__.py
raptus/recipe/torii/tests/__init__.py
raptus/recipe/torii/tests/test_docs.py