Metadata-Version: 1.0
Name: raptus.recipe.torii
Version: 1.0b1
Summary: buildout recipe for installing torii
Home-page: http://svn.plone.org/svn/collective/raptus.recipe.torii
Author: sriolo
Author-email: sriolo@raptus.com
License: GPL
Keywords: zope remote prompt zodb
Platform: UNKNOWN
Classifier: Framework :: Plone
Classifier: Framework :: Zope2
Classifier: Framework :: Zope3
Classifier: Framework :: ZODB
Classifier: Programming Language :: Python
